setup.py
rmbi3310/__init__.py
rmbi3310/data.py
rmbi3310/metrics.py
rmbi3310/regression.py
rmbi3310/risk.py
rmbi3310/timeseries.py
rmbi3310.egg-info/Icon
rmbi3310.egg-info/PKG-INFO
rmbi3310.egg-info/SOURCES.txt
rmbi3310.egg-info/dependency_links.txt
rmbi3310.egg-info/requires.txt
rmbi3310.egg-info/top_level.txt